README.md
setup.py
/Users/solbrig/git/biolink-continuous/biolink-model/BiolinkMG.egg-info/PKG-INFO
/Users/solbrig/git/biolink-continuous/biolink-model/BiolinkMG.egg-info/SOURCES.txt
/Users/solbrig/git/biolink-continuous/biolink-model/BiolinkMG.egg-info/dependency_links.txt
/Users/solbrig/git/biolink-continuous/biolink-model/BiolinkMG.egg-info/entry_points.txt
/Users/solbrig/git/biolink-continuous/biolink-model/BiolinkMG.egg-info/requires.txt
/Users/solbrig/git/biolink-continuous/biolink-model/BiolinkMG.egg-info/top_level.txt
BiolinkMG.egg-info/PKG-INFO
BiolinkMG.egg-info/SOURCES.txt
BiolinkMG.egg-info/dependency_links.txt
BiolinkMG.egg-info/entry_points.txt
BiolinkMG.egg-info/requires.txt
BiolinkMG.egg-info/top_level.txt
metamodel/__init__.py
metamodel/metamodel.py
metamodel/generators/__init__.py
metamodel/generators/contextgen.py
metamodel/generators/csvgen.py
metamodel/generators/dotgen.py
metamodel/generators/golrgen.py
metamodel/generators/graphqlgen.py
metamodel/generators/jsonldgen.py
metamodel/generators/jsonschemagen.py
metamodel/generators/markdowngen.py
metamodel/generators/owlgen.py
metamodel/generators/protogen.py
metamodel/generators/pythongen.py
metamodel/generators/rdfgen.py
metamodel/generators/shexgen.py
metamodel/generators/yumlgen.py
metamodel/utils/__init__.py
metamodel/utils/builtins.py
metamodel/utils/comparefiles.py
metamodel/utils/formatutils.py
metamodel/utils/generator.py
metamodel/utils/loadschema.py
metamodel/utils/mergeutils.py
metamodel/utils/metamodelcore.py
metamodel/utils/namespaces.py
metamodel/utils/schemaloader.py
metamodel/utils/schemasynopsis.py
metamodel/utils/typereferences.py
metamodel/utils/yamlutils.py
tests/test_issues/__init__.py
tests/test_issues/test_issue_120.py
tests/test_issues/test_issue_14.py
tests/test_issues/test_no_name_id.py
tests/test_scripts/__init__.py
tests/test_scripts/clicktestcase.py
tests/test_scripts/test_gen_csv.py
tests/test_scripts/test_gen_golr.py
tests/test_scripts/test_gen_graphql.py
tests/test_scripts/test_gen_json_schema.py
tests/test_scripts/test_gen_jsonld.py
tests/test_scripts/test_gen_jsonld_context.py
tests/test_scripts/test_gen_markdown.py
tests/test_scripts/test_gen_owl.py
tests/test_scripts/test_gen_proto.py
tests/test_scripts/test_gen_python.py
tests/test_scripts/test_gen_rdf.py
tests/test_scripts/test_gen_shex.py
tests/test_scripts/test_gen_yuml.py
tests/test_scripts/testnm_gen_graphviz.py
tests/utils/GeneratorTestCase.py
tests/utils/__init__.py
tests/utils/dirutils.py